tdwnsv3/__init__.py
tdwnsv3/__main__.py
tdwnsv3/admin.py
tdwnsv3/ciphersuite.py
tdwnsv3/fav.py
tdwnsv3/html_prettier.py
tdwnsv3/javascript.py
tdwnsv3/sec_server.py
tdwnsv3/style.py
tdwnsv3/tdwnsv3.py
tdwnsv3-1.9.5.dist-info/LICENSE
tdwnsv3-1.9.5.dist-info/METADATA
tdwnsv3-1.9.5.dist-info/WHEEL
tdwnsv3-1.9.5.dist-info/entry_points.txt
tdwnsv3-1.9.5.dist-info/top_level.txt
tdwnsv3-1.9.5.dist-info/RECORD
