Metadata-Version: 2.1
Name: tdwnsv3
Version: 1.9.5
Summary: Simple local-files server with security on top!
Home-page: https://github.com/Simatwa/tdwnsv3
Author: Smartwa Caleb
Author-email: smartwacaleb@gmail.com
Maintainer: Smartwa Caleb
Maintainer-email: smartwacaleb@gmail.com
License: MIT
Project-URL: Bug Report, https://github.com/Simatwa/tdwnsv3/issues/new
Classifier: License :: OSI Approved :: MIT License
Classifier: Programming Language :: Python :: 3
Classifier: Programming Language :: Python :: 3.7
Classifier: Programming Language :: Python :: 3.8
Classifier: Programming Language :: Python :: 3.9
Classifier: Programming Language :: Python :: 3.10
Classifier: Programming Language :: Python :: 3.11
License-File: LICENSE
Requires-Dist: Flask ==2.2.2
Requires-Dist: cryptography ==39.0.0
Requires-Dist: appdirs ==1.4.4
Requires-Dist: Flask-Admin ==1.6.1
Requires-Dist: Werkzeug ==2.2.2
